simpledi/__init__.py
simpledi-0.4.1.dist-info/LICENSE
simpledi-0.4.1.dist-info/METADATA
simpledi-0.4.1.dist-info/WHEEL
simpledi-0.4.1.dist-info/top_level.txt
simpledi-0.4.1.dist-info/RECORD
